django_keycloak/__init__.py
django_keycloak/app_settings.py
django_keycloak/apps.py
django_keycloak/factories.py
django_keycloak/hashers.py
django_keycloak/middleware.py
django_keycloak/models.py
django_keycloak/remote_user.py
django_keycloak/response.py
django_keycloak/urls.py
django_keycloak/views.py
django_keycloak/admin/__init__.py
django_keycloak/admin/realm.py
django_keycloak/admin/server.py
django_keycloak/auth/__init__.py
django_keycloak/auth/backends.py
django_keycloak/management/__init__.py
django_keycloak/management/commands/__init__.py
django_keycloak/management/commands/keycloak_add_user.py
django_keycloak/management/commands/keycloak_refresh_realm.py
django_keycloak/management/commands/keycloak_sync_resources.py
django_keycloak/migrations/0001_initial.py
django_keycloak/migrations/0002_auto_20180322_2059.py
django_keycloak/migrations/0003_auto_20190204_1949.py
django_keycloak/migrations/0004_client_service_account_profile.py
django_keycloak/migrations/0005_auto_20190219_2002.py
django_keycloak/migrations/0006_remove_client_service_account.py
django_keycloak/migrations/0007_alter_client_id_alter_exchangedtoken_id_and_more.py
django_keycloak/migrations/__init__.py
django_keycloak/services/__init__.py
django_keycloak/services/client.py
django_keycloak/services/exceptions.py
django_keycloak/services/oidc_profile.py
django_keycloak/services/permissions.py
django_keycloak/services/realm.py
django_keycloak/services/remote_client.py
django_keycloak/services/uma.py
django_keycloak/services/users.py
django_keycloak/tests/__init__.py
django_keycloak/tests/mixins.py
django_keycloak/tests/settings.py
django_keycloak/tests/backends/__init__.py
django_keycloak/tests/backends/keycloak_authorization_base/__init__.py
django_keycloak/tests/backends/keycloak_authorization_base/test_get_keycloak_permissions.py
django_keycloak/tests/backends/keycloak_authorization_base/test_has_perm.py
django_keycloak/tests/services/__init__.py
django_keycloak_pkg-0.2.5.dist-info/LICENSE
django_keycloak_pkg-0.2.5.dist-info/METADATA
django_keycloak_pkg-0.2.5.dist-info/WHEEL
django_keycloak_pkg-0.2.5.dist-info/top_level.txt
django_keycloak_pkg-0.2.5.dist-info/RECORD
